[{"frame_index_start":2,"frame_index_end":2,"type":"navigate","description":"User navigates to the Studies page","confidence":0.9,"page_title":"Studies","page_location":"app.askable.com/studies","frame_description":"The Studies page loads showing a list of research studies."},{"frame_index_start":20,"frame_index_end":22,"type":"navigate","description":"User clicks on the 'Askable | Opportunities' tab and navigates to the opportunity details page","confidence":0.95,"interaction_target":"Askable | Opportunities tab","page_title":"Askable | Opportunities","page_location":"my-dev.askable.com/opportunities/699e35dab2c3fe94d25e6d94","frame_description":"The user switches browser tabs to view a specific opportunity titled 'Internal AI Mod website test'."},{"frame_index_start":24,"frame_index_end":26,"type":"navigate","description":"User clicks back on the 'Studies' tab to return to the studies list","confidence":0.95,"interaction_target":"Studies tab","page_title":"Studies","page_location":"app.askable.com/studies","frame_description":"The user switches back to the original Studies tab."},{"frame_index_start":27,"frame_index_end":30,"type":"hover","description":"User hovers over the 'AI Moderated' type label in the studies table","confidence":0.8,"interaction_target":"AI Moderated label","page_title":"Studies","frame_description":"The cursor lingers over the study type column for the 'James Study'."}]