[{"frame_index_start":2,"frame_index_end":2,"type":"click","description":"User clicks the next month arrow in the calendar to view October and November 2026","confidence":0.9,"interaction_target":"Next month arrow in calendar","page_title":"Hostels Worldwide","page_location":"hostelworld.com/","frame_description":"The user is interacting with the date picker on the Hostelworld homepage."},{"frame_index_start":5,"frame_index_end":5,"type":"select","description":"User selects November 9th as the check-in date","confidence":0.9,"interaction_target":"November 9th in calendar","page_title":"Hostels Worldwide","page_location":"hostelworld.com/","frame_description":"The user selects the start date for their stay."},{"frame_index_start":6,"frame_index_end":6,"type":"select","description":"User selects November 15th as the check-out date","confidence":0.9,"interaction_target":"November 15th in calendar","page_title":"Hostels Worldwide","page_location":"hostelworld.com/","frame_description":"The user selects the end date for their stay, completing the date range selection."},{"frame_index_start":7,"frame_index_end":7,"type":"click","description":"User clicks the 'Let's go!' button to search for hostels","confidence":0.95,"interaction_target":"Let's go! button","page_title":"Hostels Worldwide","page_location":"hostelworld.com/","frame_description":"The user initiates the search with the selected dates and location."},{"frame_index_start":8,"frame_index_end":10,"type":"navigate","description":"The page navigates to the search results for London","confidence":1.0,"page_title":"Hostels in London","page_location":"hostelworld.com/pwa/s?q=London, England","frame_description":"The browser loads the search results page showing available hostels."},{"frame_index_start":11,"frame_index_end":15,"type":"dwell","description":"User examines the search results, hovering over hostel listings","confidence":0.8,"page_title":"Hostels in London","page_location":"hostelworld.com/pwa/s?q=London, England","frame_description":"The user pauses to look at the list of hostels, including Palmers Lodge and Wombat's City Hostel."},{"frame_index_start":16,"frame_index_end":16,"type":"click","description":"User clicks the 'Map' button to switch to map view","confidence":0.9,"interaction_target":"Map button","page_title":"Hostels in London","page_location":"hostelworld.com/pwa/s?q=London, England","frame_description":"The user clicks the map icon in the top right of the results list."},{"frame_index_start":17,"frame_index_end":17,"type":"change_ui_state","description":"The UI updates to show a map of hostel locations alongside the list","confidence":0.95,"page_title":"Hostels in London","page_location":"hostelworld.com/pwa/s?q=London, England","frame_description":"The screen layout changes to include an interactive map."}]